federated_aggregation/__init__.py
federated_aggregation/aggregator.py
federated_aggregation/central_re_embedding.py
federated_aggregation/naive_conf_reranking.py
federated_aggregation/procrustes_method.py
federated_aggregation/rrp_bm25.py
federated_aggregation-0.1.0.dist-info/licenses/LICENSE
federated_aggregation-0.1.0.dist-info/METADATA
federated_aggregation-0.1.0.dist-info/WHEEL
federated_aggregation-0.1.0.dist-info/top_level.txt
federated_aggregation-0.1.0.dist-info/RECORD
