Metadata-Version: 2.4
Name: federated_aggregation
Version: 0.1.0
Summary: A library for aggregating and re-ranking information from multi-source federated retrieval systems
Home-page: https://github.com/siddhant230/Aggregator_package
Author: Siddhant Rai
Author-email: rsiddhant73@gmail.com
Project-URL: Bug Tracker, https://github.com/siddhant230/Aggregator_package/issues
Project-URL: Documentation, https://github.com/siddhant230/Aggregator_package#readme
Project-URL: Source Code, https://github.com/siddhant230/Aggregator_package
Keywords: federated,aggregation,reranking,rag,embeddings,search,retrieval,nlp
Classifier: Development Status :: 3 - Alpha
Classifier: Intended Audience :: Developers
Classifier: Intended Audience :: Science/Research
Classifier: License :: OSI Approved :: MIT License
Classifier: Operating System :: OS Independent
Classifier: Programming Language :: Python :: 3
Classifier: Programming Language :: Python :: 3.8
Classifier: Programming Language :: Python :: 3.9
Classifier: Programming Language :: Python :: 3.10
Classifier: Programming Language :: Python :: 3.11
Classifier: Programming Language :: Python :: 3.12
Classifier: Topic :: Scientific/Engineering :: Artificial Intelligence
Classifier: Topic :: Text Processing :: Linguistic
Requires-Python: >=3.8
License-File: LICENSE
Requires-Dist: numpy
Requires-Dist: fastembed
Requires-Dist: scikit-learn
Requires-Dist: rank-bm25
Requires-Dist: pytest
Provides-Extra: dev
Requires-Dist: pytest>=7.0.0; extra == "dev"
Requires-Dist: pytest-cov>=4.0.0; extra == "dev"
Requires-Dist: black>=23.0.0; extra == "dev"
Requires-Dist: isort>=5.12.0; extra == "dev"
Requires-Dist: mypy>=1.0.0; extra == "dev"
Dynamic: author
Dynamic: author-email
Dynamic: classifier
Dynamic: description
Dynamic: description-content-type
Dynamic: home-page
Dynamic: keywords
Dynamic: license-file
Dynamic: project-url
Dynamic: provides-extra
Dynamic: requires-dist
Dynamic: requires-python
Dynamic: summary
